jwtsign-1.0.8.dist-info/top_level.txt
jwtsign-1.0.8.dist-info/WHEEL
jwtsign-1.0.8.dist-info/METADATA
jwtsign-1.0.8.dist-info/RECORD
jwtsign/jwtsign.cpython-37m-x86_64-linux-gnu.so
jwtsign/version.py
jwtsign/__init__.py
jwtsign/jwtsign.pyi
