Metadata-Version: 2.1
Name: jwtsign
Version: 1.0.8
Summary: JWT encoding and decoding limited to RS256
Home-page: https://github.com/kruhlmann/jwtsign
Classifier: Programming Language :: Python
Classifier: Programming Language :: Rust
Requires-Python: >=3.10
